[
  {
    "firstName": "John",
    "middleName": "A.",
    "lastName": "Doe",
    "status": "Unclaimed",
    "action": "View"
  },
  {
    "firstName": "Jane",
    "middleName": "B.",
    "lastName": "Smith",
    "status": "Claimed",
    "action": "View"
  },
  {
    "firstName": "Alice",
    "middleName": "C.",
    "lastName": "Johnson",
    "status": "Unclaimed",
    "action": "View"
  },
  {
    "firstName": "Bob",
    "middleName": "D.",
    "lastName": "Brown",
    "status": "Claimed",
    "action": "View"
  },
  {
    "firstName": "Charlie",
    "middleName": "E.",
    "lastName": "Davis",
    "status": "Unclaimed",
    "action": "View"
  },
  {
    "firstName": "David",
    "middleName": "F.",
    "lastName": "Evans",
    "status": "Claimed",
    "action": "View"
  },
  {
    "firstName": "Ella",
    "middleName": "G.",
    "lastName": "Wilson",
    "status": "Unclaimed",
    "action": "View"
  },
  {
    "firstName": "Frank",
    "middleName": "H.",
    "lastName": "Thomas",
    "status": "Claimed",
    "action": "View"
  },
  {
    "firstName": "Grace",
    "middleName": "I.",
    "lastName": "Moore",
    "status": "Unclaimed",
    "action": "View"
  },
  {
    "firstName": "Henry",
    "middleName": "J.",
    "lastName": "Taylor",
    "status": "Claimed",
    "action": "View"
  },
  {
    "firstName": "Isabella",
    "middleName": "K.",
    "lastName": "Anderson",
    "status": "Unclaimed",
    "action": "View"
  }
]
